{
  "users": [
    {
      "id": "84d2",
      "user": "Santiago",
      "password": "123456",
      "email": "santiago@gmail.com"
    }
  ],
  "products": [
    {
      "name": "Café con leche de San Miguel",
      "description": "Café con leche ",
      "price": "7000",
      "src": "https://www.clarin.com/img/2023/09/29/3FXDyDjlw_2000x1500__1.jpg",
      "category": "cafeteria",
      "id": "0dfd"
    },
    {
      "id": "cf33",
      "name": "Chocolate con pasas",
      "description": "Delicioso chocalte de cacao puro",
      "price": "7000",
      "src": "https://acdn.mitiendanube.com/stores/002/625/145/products/pasas-choco1-d2c2ab9b7b4649b91c16793396210983-1024-1024.jpg",
      "category": "cafeteria"
    }
  ]
}